deepszsim/__init__.py
deepszsim/dm_halo_dist.py
deepszsim/filters.py
deepszsim/io_params.py
deepszsim/load_vars.py
deepszsim/make_sz_cluster.py
deepszsim/noise.py
deepszsim/read_yaml.py
deepszsim/simclusters.py
deepszsim/simtools.py
deepszsim/utils.py
deepszsim/visualization.py
deepszsim/Settings/config_everything.yaml
deepszsim/Settings/config_simACTDR5.yaml
deepszsim-0.1.1.dist-info/LICENSE
deepszsim-0.1.1.dist-info/METADATA
deepszsim-0.1.1.dist-info/WHEEL
deepszsim-0.1.1.dist-info/top_level.txt
deepszsim-0.1.1.dist-info/RECORD
