Metadata-Version: 2.1
Name: deepszsim
Version: 0.1.1
Summary: code for fast simulations of galaxy clusters
Author-email: Eve Vavagiakis <ev66@cornell.edu>
License: LICENSE.txt
Requires-Python: <3.12,>=3.9
License-File: LICENSE
Requires-Dist: camb >=1.4.0
Requires-Dist: h5py >=3.8.0
Requires-Dist: numpy <2,>=1.24.3
Requires-Dist: astropy >=6.0
Requires-Dist: colossus >=1.3.0
Requires-Dist: tqdm >=4.66.0
Requires-Dist: pixell ==0.17.3
